LICENSE
MANIFEST.in
README.md
setup.cfg
setup.py
kaggle/__init__.py
kaggle/api_client.py
kaggle/cli.py
kaggle/configuration.py
kaggle/rest.py
kaggle/api/__init__.py
kaggle/api/kaggle_api.py
kaggle/api/kaggle_api_extended.py
kaggle/models/__init__.py
kaggle/models/collaborator.py
kaggle/models/dataset_column.py
kaggle/models/dataset_new_request.py
kaggle/models/dataset_new_version_request.py
kaggle/models/dataset_update_settings_request.py
kaggle/models/dataset_upload_file.py
kaggle/models/error.py
kaggle/models/file.py
kaggle/models/kaggle_models_extended.py
kaggle/models/kernel_push_request.py
kaggle/models/license.py
kaggle/models/result.py
kaggle/tests/__init__.py
kaggle/tests/test_authenticate.py
yektatestapi.egg-info/PKG-INFO
yektatestapi.egg-info/SOURCES.txt
yektatestapi.egg-info/dependency_links.txt
yektatestapi.egg-info/entry_points.txt
yektatestapi.egg-info/requires.txt
yektatestapi.egg-info/top_level.txt