Metadata-Version: 2.1
Name: yektatestapi
Version: 0.0.3
Summary: test API
Author: yekta
Author-email: yekta1@live.com
License: Apache 2.0
Keywords: test,API
License-File: LICENSE
